LICENSE.rst
MANIFEST.in
Makefile
NEWS.rst
README.rst
TODO.rst
requirements.txt
setup.cfg
setup.py
doc/api.rst
doc/conf.py
doc/development.rst
doc/faq.rst
doc/index.rst
doc/installation.rst
doc/license.rst
doc/news.rst
doc/todo.rst
doc/user.rst
happybase/__init__.py
happybase/_version.py
happybase/batch.py
happybase/connection.py
happybase/pool.py
happybase/table.py
happybase/util.py
happybase.egg-info/PKG-INFO
happybase.egg-info/SOURCES.txt
happybase.egg-info/dependency_links.txt
happybase.egg-info/requires.txt
happybase.egg-info/top_level.txt
happybase/hbase/Hbase.py
happybase/hbase/__init__.py
happybase/hbase/constants.py
happybase/hbase/ttypes.py
tests/__init__.py
tests/test_api.py
tests/test_util.py